netlink/logging/__init__.py
netlink/logging/__init__.pyi
netlink/logging/_logging.py
netlink_logging-0.1.15.dist-info/LICENSE.md
netlink_logging-0.1.15.dist-info/WHEEL
netlink_logging-0.1.15.dist-info/METADATA
netlink_logging-0.1.15.dist-info/RECORD
