Metadata-Version: 2.1
Name: netlink-logging
Version: 0.1.15
Summary: A wrapper around logging and logzero
Home-page: https://gitlab.com/netlink-consulting/netlink-logging
License: MIT
Keywords: logging
Author: Bernhard Radermacher
Author-email: bernhard.radermacher@netlink-consulting.com
Requires-Python: >=3.8,<=3.12
Classifier: License :: OSI Approved :: MIT License
Classifier: Programming Language :: Python :: 3
Classifier: Programming Language :: Python :: 3.10
Classifier: Programming Language :: Python :: 3.8
Classifier: Programming Language :: Python :: 3.9
Classifier: Topic :: Software Development
Requires-Dist: logzero (>=1.7.0)
Requires-Dist: netlink-core (>=1.1.2)
Project-URL: Repository, https://gitlab.com/netlink-consulting/netlink-logging
